opensemantic/__init__.py
opensemantic/_model.py
opensemantic/custom_types.py
opensemantic/v1/__init__.py
opensemantic/v1/_model.py
opensemantic-0.2.0.dist-info/licenses/LICENSE.txt
opensemantic-0.2.0.dist-info/METADATA
opensemantic-0.2.0.dist-info/WHEEL
opensemantic-0.2.0.dist-info/top_level.txt
opensemantic-0.2.0.dist-info/RECORD
