Metadata-Version: 2.4
Name: opensemantic
Version: 0.2.0
Summary: This is the top-level Python namespace package for libraries with Python models derived from page packages that reside under world.opensemantic
Home-page: https://github.com/OpenSemanticWorld-Packages/opensemantic-python
Author: OpenSemanticWorld
Author-email: team@opensemantic.world
License: Apache 2.0
Project-URL: Documentation, https://github.com/OpenSemanticWorld-Packages/opensemantic-python
Project-URL: Source, https://github.com/OpenSemanticWorld-Packages/opensemantic-python
Project-URL: Tracker, https://github.com/OpenSemanticWorld-Packages/opensemantic-python/issues
Platform: any
Classifier: Development Status :: 4 - Beta
Classifier: Programming Language :: Python
Requires-Python: >=3.10
License-File: LICENSE.txt
Requires-Dist: oold
Requires-Dist: backports.strenum; python_version < "3.11"
Provides-Extra: testing
Requires-Dist: setuptools; extra == "testing"
Requires-Dist: pytest; extra == "testing"
Requires-Dist: pytest-cov; extra == "testing"
Dynamic: license-file
